tetkit/__init__.py
tetkit/db/__init__.py
tetkit/db/alembic.py
tetkit/db/base.py
tetkit/decorator/auth.py
tetkit/script/base.py
tetkit/security/cors.py
tetkit/testing/fixtures.py
tetkit/utils.py
tetkit-0.1.6.dist-info/METADATA
tetkit-0.1.6.dist-info/WHEEL
tetkit-0.1.6.dist-info/entry_points.txt
tetkit-0.1.6.dist-info/RECORD
